{
  "realm": "fuz",
  "enabled": true,
  "clients": [
    {
      "clientId": "fusionize-orchestrator",
      "secret": "fusionize-secret",
      "directAccessGrantsEnabled": true,
      "serviceAccountsEnabled": true,
      "publicClient": false,
      "protocol": "openid-connect",
      "redirectUris": ["*"]
    },
    {
      "clientId": "fusionize-workers",
      "secret": "fusionize-secret",
      "directAccessGrantsEnabled": true,
      "serviceAccountsEnabled": true,
      "publicClient": false,
      "protocol": "openid-connect",
      "redirectUris": ["*"]
    },
    {
      "clientId": "fusionize-hub",
      "directAccessGrantsEnabled": true,
      "serviceAccountsEnabled": false,
      "publicClient": true,
      "protocol": "openid-connect",
      "redirectUris": ["*"],
      "webOrigins": ["*"]
    }
  ],
  "users": [
    {
      "username": "fusionize-admin",
      "enabled": true,
      "emailVerified": true,
      "firstName": "Fusionize",
      "lastName": "Admin",
      "email": "admin@fusionize.dev",
      "credentials": [{ "type": "password", "value": "admin", "temporary": false }]
    }
  ]
}
